Metadata-Version: 2.1
Name: nonebot-plugin-picksong
Version: 1.1.4
Summary: nonebot2点歌插件
Author: QiYork
Author-email: 1309946582@qq.com
License: MIT License
Classifier: Programming Language :: Python
Requires-Python: >=3.8
License-File: LICENSE
Requires-Dist: nonebot2 >=2.2.0
Requires-Dist: nonebot-adapter-onebot >=2.1.5
Requires-Dist: nonebot-plugin-localstore >=0.7.0
Requires-Dist: httpx >=0.27.2
Requires-Dist: requests >=2.31.0
Requires-Dist: pydub >=0.25.1
Requires-Dist: graiax-silkcoder >=0.3.6
Requires-Dist: ffmpeg >=1.4
